django_underconstruction/__init__.py
django_underconstruction/apps.py
django_underconstruction/middleware.py
django_underconstruction/settings.py
django_underconstruction/version.py
django_underconstruction/templates/django_underconstruction/construction.html
tests/__init__.py
tests/settings.py
tests/test_middleware.py
django_underconstruction-0.1.2.dist-info/LICENSE
django_underconstruction-0.1.2.dist-info/METADATA
django_underconstruction-0.1.2.dist-info/WHEEL
django_underconstruction-0.1.2.dist-info/top_level.txt
django_underconstruction-0.1.2.dist-info/RECORD
