Metadata-Version: 2.1
Name: django-underconstruction
Version: 0.1.2
Summary: django-underconstruction shows an under construction page
Home-page: https://github.com/koenwoortman/django-underconstruction
Author: Koen Woortman
Author-email: koensw@outlook.com
License: MIT
Project-URL: Source, https://github.com/koenwoortman/django-underconstruction
Platform: UNKNOWN
Classifier: Framework :: Django
Classifier: License :: OSI Approved :: MIT License
Classifier: Programming Language :: Python :: 3
Requires-Python: >=3.6
Requires-Dist: Django (>=2.2)
